{
  "tournament": "Travelers Championship",
  "week_of": "Jun 25–28, 2026",
  "published": "2026-06-25",
  "picks": [
    {
      "player": "Aaron Rai",
      "bet_type": "Top 5",
      "bet_detail": null,
      "odds": "+1000",
      "book": "DraftKings",
      "reasoning": "Best edge on the board. DG fair +870, DK +1000 = 13.5% positive EV. Same mispricing appears in his Top 10 (+425 DK, +8.3% EV) and outright win (+5500 DK, +6.5% EV). Also the free pick this week.",
      "confidence": "Medium",
      "result": null,
      "result_detail": null
    },
    {
      "player": "Russell Henley",
      "bet_type": "Top 5",
      "bet_detail": null,
      "odds": "+660",
      "book": "DraftKings",
      "reasoning": "Only book above DG fair in the Top 5 market — DK +660 vs. fair +640 (+2.7% EV). Won the Schwab Challenge at Colonial this season, a near-identical course-fit profile (App-heavy, Putt-heavy). Ranks #27 in SG: Approach.",
      "confidence": "Medium",
      "result": null,
      "result_detail": null
    },
    {
      "player": "Sepp Straka",
      "bet_type": "Top 10",
      "bet_detail": null,
      "odds": "+900",
      "book": "FanDuel",
      "reasoning": "Best EV of any Top 10 bet on the board. DG fair +805, FD +900 = 10.5% positive EV. Same mispricing in Top 20 (FD +340, +7.6% EV). Ranks #25 in SG: Approach. Market consistently underrates him relative to the model.",
      "confidence": "Medium",
      "result": null,
      "result_detail": null
    },
    {
      "player": "Tommy Fleetwood",
      "bet_type": "Top 10",
      "bet_detail": null,
      "odds": "+175",
      "book": "FanDuel",
      "reasoning": "One of two players in the field on both the top-33 SG: Approach (#18) and top-32 SG: Putting (#25) lists. TPC River Highlands rewards both (App 28%, Putt 32%). Near-fair at +175 (DG fair +185); this is a course-fit conviction bet, not a market-edge bet.",
      "confidence": "Medium",
      "result": null,
      "result_detail": null
    },
    {
      "player": "Kurt Kitayama",
      "bet_type": "Top 5",
      "bet_detail": null,
      "odds": "+1000",
      "book": "FanDuel",
      "reasoning": "Ranks #9 in SG: Approach in this field. DG fair +971, FD +1000 = 2.7% positive EV. Quietly solid season — had a Top 10 at the PGA Championship (+800, which hit). At the +1000 cap, the approach profile and mild model edge justify the inclusion.",
      "confidence": "Low",
      "result": null,
      "result_detail": null
    },
    {
      "player": "Si Woo Kim",
      "bet_type": "Top 10",
      "bet_detail": null,
      "odds": "+260",
      "book": "Caesars",
      "reasoning": "Best EV in the shorter-price tier at 6.7%. DG fair +237, Caesars +260. Approach #6 in this field — same case as the longer-priced plays above, just a wider net at proportionally shorter odds.",
      "confidence": "Medium",
      "result": null,
      "result_detail": null,
      "section": "Shorter-Price Plays"
    },
    {
      "player": "Patrick Cantlay",
      "bet_type": "Top 10",
      "bet_detail": null,
      "odds": "+300",
      "book": "FanDuel",
      "reasoning": "Approach #8 in this field. DG fair +295, FD +300 = 1.2% positive EV. Slim edge but real course fit — 28% approach weight suits his profile. Missed the cut at the U.S. Open but consistent elsewhere this season.",
      "confidence": "Medium",
      "result": null,
      "result_detail": null
    },
    {
      "player": "J.J. Spaun",
      "bet_type": "Top 20",
      "bet_detail": null,
      "odds": "+160",
      "book": "FanDuel",
      "reasoning": "Approach #2 in this field. DG fair +156, FD +160 = 1.4% positive EV. Wider net version of the Spaun case — he just needs a top-20 finish rather than a top-10. Lower variance entry on the same course-fit profile.",
      "confidence": "Medium",
      "result": null,
      "result_detail": null
    }
  ]
}
